cs_ai_common/__init__.py
cs_ai_common/crypto/__init__.py
cs_ai_common/crypto/fernet.py
cs_ai_common/dynamodb/__init__.py
cs_ai_common/dynamodb/resolver_task_table.py
cs_ai_common/dynamodb/task_table.py
cs_ai_common/dynamodb/utils.py
cs_ai_common/logging/__init__.py
cs_ai_common/logging/internal_logger.py
cs_ai_common/middlewares/__init__.py
cs_ai_common/middlewares/exception_handler.py
cs_ai_common/models/__init__.py
cs_ai_common/models/filters.py
cs_ai_common/models/pagination.py
cs_ai_common/models/resolvers.py
cs_ai_common/models/sort.py
cs_ai_common/proxy/__init__.py
cs_ai_common/proxy/proxy_client.py
cs_ai_common/rds/__init__.py
cs_ai_common/rds/db_connection.py
cs_ai_common/rds/db_session.py
cs_ai_common/rds/entities/__init__.py
cs_ai_common/rds/entities/advertisement.py
cs_ai_common/rds/entities/base.py
cs_ai_common/rds/entities/external_site.py
cs_ai_common/rds/entities/external_site_instance.py
cs_ai_common/rds/entities/location.py
cs_ai_common/rds/entities/offer.py
cs_ai_common/rds/entities/offer_instances.py
cs_ai_common/rds/entities/offer_site_instance.py
cs_ai_common/rds/entities/user.py
cs_ai_common/rds/utils/__init__.py
cs_ai_common/rds/utils/create_db_schema.py
cs_ai_common/resolver_cache/__init__.py
cs_ai_common/resolver_cache/cache_key.py
cs_ai_common/resolver_cache/s3_cache_utils.py
cs_ai_common/resolver_cache/try_get_cache.py
cs_ai_common/resolver_stats/__init__.py
cs_ai_common/resolver_stats/stats.py
cs_ai_common/s3/__init__.py
cs_ai_common/s3/resolver_results.py
cs_ai_common/s3/utils.py
cs_ai_common/seed_data/__init__.py
cs_ai_common/seed_data/lambda_event_seed_data_resolver.py
cs_ai_common/seed_data/seed_data_resolver.py
cs_ai_common/services/__init__.py
cs_ai_common/services/result_writer_service.py
cs_ai_common/services/s3_result_writer_service.py
cs_ai_common/startup/__init__.py
cs_ai_common/startup/startup.py
cs_ai_common/typings/__init__.py
cs_ai_common/typings/car_utils.py
cs_ai_common/typings/price_utils.py
cs_ai_common-0.6.1.dist-info/METADATA
cs_ai_common-0.6.1.dist-info/WHEEL
cs_ai_common-0.6.1.dist-info/RECORD
