Metadata-Version: 2.1
Name: cs-ai-common
Version: 0.6.1
Summary: 
Author: Adrian Gajewski
Author-email: adrian.gajewski001@gmail.com
Requires-Python: >=3.12,<4.0
Classifier: Programming Language :: Python :: 3
Classifier: Programming Language :: Python :: 3.12
Classifier: Programming Language :: Python :: 3.13
Requires-Dist: PyJWT (>=2.9.0,<3.0.0)
Requires-Dist: SQLAlchemy (>=2.0.36,<3.0.0)
Requires-Dist: boto3 (>=1.35.39,<2.0.0)
Requires-Dist: cryptography (>=43.0.3,<44.0.0)
Requires-Dist: fastapi (>=0.115.2,<0.116.0)
Requires-Dist: psycopg2-binary (>=2.9.10,<3.0.0)
Requires-Dist: pycryptodome (>=3.21.0,<4.0.0)
Requires-Dist: pydantic (>=2.9.2,<3.0.0)
